bch_foo/__init__.py
bch_foo/bch_foo.py
bch_foo/cli.py
bch_foo/install.py
bch_foo/math.py
bch_foo/util.py
bch_foo/data/bh.bump
bch_foo/data/bumpversion.cfg
bch_foo/data/init4repo4user4vis.sh
bch_foo-0.1.4.data/scripts/bh.bump
bch_foo-0.1.4.dist-info/AUTHORS.rst
bch_foo-0.1.4.dist-info/LICENSE
bch_foo-0.1.4.dist-info/METADATA
bch_foo-0.1.4.dist-info/WHEEL
bch_foo-0.1.4.dist-info/entry_points.txt
bch_foo-0.1.4.dist-info/top_level.txt
bch_foo-0.1.4.dist-info/RECORD
