Metadata-Version: 2.1
Name: bch-foo
Version: 0.1.4
Summary: a spike
Author-email: Bryan Hann <nobody@nowhere.com>
Maintainer-email: Bryan Hann <nobody@nowhere.com>
License: MIT license
Project-URL: bugs, https://github.com/bryanhann/bch_foo/issues
Project-URL: changelog, https://github.com/bryanhann/bch_foo/blob/master/changelog.md
Project-URL: homepage, https://github.com/bryanhann/bch_foo
Requires-Python: >=3.12
License-File: LICENSE
License-File: AUTHORS.rst
Requires-Dist: bump2version >=1.0.1
Provides-Extra: dev
